{
  "$schema": "https://schema.tauri.app/config/2",
  "identifier": "bancodequestoes",
  "productName": "Banco de Questões",
  "version": "1.0.0",
  "build": {
    "beforeBuildCommand": "pnpm run build",
    "beforeDevCommand": "pnpm run dev",
    "frontendDist": "../dist",
    "devUrl": "http://localhost:5173"
  },
  "app": {
    "windows": [
      {
        "title": "Banco de Questões",
        "width": 1200,
        "height": 800,
        "resizable": true
      }
    ],
    "security": {
      "csp": null
    }
  },
  "bundle": {
    "active": true,
    "targets": "all",
    "icon": ["icons/icon.ico", "icons/icon.png", "icons/icon.icns"]
  }
}
